setup.py
mdxflavours/__init__.py
mdxflavours/mdx_autobr.py
mdxflavours/mdx_autolink.py
mdxflavours.egg-info/PKG-INFO
mdxflavours.egg-info/SOURCES.txt
mdxflavours.egg-info/dependency_links.txt
mdxflavours.egg-info/requires.txt
mdxflavours.egg-info/top_level.txt