Metadata-Version: 1.0
Name: mdxflavours
Version: 0.9
Summary: Markdown extensions for basic syntax flavoring.
Home-page: https://github.com/05bit/python-mdxflavours
Author: Alexey Kinyov
Author-email: rudy@05bit.com
License: BSD
Keywords: markdown,extensions
Platform: UNKNOWN
Classifier: Development Status :: 4 - Beta
Classifier: Operating System :: OS Independent
Classifier: License :: OSI Approved :: BSD License
Classifier: Intended Audience :: Developers
Classifier: Environment :: Web Environment
Classifier: Programming Language :: Python :: 2.5
Classifier: Programming Language :: Python :: 2.6
Classifier: Programming Language :: Python :: 2.7
Classifier: Topic :: Text Processing :: Filters
Classifier: Topic :: Text Processing :: Markup :: HTML
